cqfbt/__init__.py
cqfbt/backtester.py
cqfbt/strategy.py
cqfbt-1.0.1.dist-info/LICENSE.md
cqfbt-1.0.1.dist-info/METADATA
cqfbt-1.0.1.dist-info/WHEEL
cqfbt-1.0.1.dist-info/RECORD
