Metadata-Version: 2.1
Name: cqfbt
Version: 1.0.1
Summary: 
Author: Jack Young
Author-email: 59127086+JackRYoung@users.noreply.github.com
Requires-Python: >=3.10,<4.0
Classifier: Programming Language :: Python :: 3
Classifier: Programming Language :: Python :: 3.10
Classifier: Programming Language :: Python :: 3.11
Requires-Dist: python-dotenv (>=1.0.0,<2.0.0)
Requires-Dist: requests (>=2.31.0,<3.0.0)
